pysdi/__init__.py
pysdi/drought_definition.py
pysdi-0.2.6.3.1.dist-info/LICENSE.txt
pysdi-0.2.6.3.1.dist-info/METADATA
pysdi-0.2.6.3.1.dist-info/WHEEL
pysdi-0.2.6.3.1.dist-info/top_level.txt
pysdi-0.2.6.3.1.dist-info/RECORD
