Metadata-Version: 2.1
Name: pysdi
Version: 0.2.6.3.1
Summary: Calculator of non-parametric standardized drought indices.
Home-page: https://bitbucket.org/pysdi/pysdi
Author: R. A. Real-Rangel
Author-email: rrealr@iingen.unam.mx
License: GPL-3.0
Keywords: standardized drought index SPI
Platform: UNKNOWN
Classifier: Development Status :: 4 - Beta
Classifier: Topic :: Scientific/Engineering :: Hydrology
Classifier: License :: OSI Approved :: GNU General Public License v3 (GPLv3)
Requires-Dist: datetime
Requires-Dist: dask
Requires-Dist: netcdf4
Requires-Dist: numpy
Requires-Dist: pathlib2
Requires-Dist: scipy
Requires-Dist: toml
Requires-Dist: toolz
Requires-Dist: xarray
